algorhino_coral-0.1.8.dist-info/licenses/LICENSE
coral/__init__.py
coral/board_evaluation.py
coral/chi_nn.py
coral/neural_networks/__init__.py
coral/neural_networks/factory.py
coral/neural_networks/neural_net_architecture_args.py
coral/neural_networks/neural_net_board_eval_args.py
coral/neural_networks/nn_model_type.py
coral/neural_networks/nn_model_type_args.py
coral/neural_networks/nn_state_evaluator.py
coral/neural_networks/input_converters/__init__.py
coral/neural_networks/input_converters/content_to_input.py
coral/neural_networks/models/__init__.py
coral/neural_networks/models/multi_layer_perceptron.py
coral/neural_networks/models/transformer_one.py
coral/neural_networks/output_converters/__init__.py
coral/neural_networks/output_converters/factory.py
coral/neural_networks/output_converters/model_output_type.py
coral/neural_networks/output_converters/output_value_converter.py
coral/utils/logger.py
coral/utils/small_tools.py
algorhino_coral-0.1.8.dist-info/METADATA
algorhino_coral-0.1.8.dist-info/WHEEL
algorhino_coral-0.1.8.dist-info/top_level.txt
algorhino_coral-0.1.8.dist-info/RECORD
