Metadata-Version: 2.4
Name: algorhino-coral
Version: 0.1.8
Summary: Shared types and utilities for evalaution
Author-email: Victor Gabillon <victorgabillon@gmail.com>
License-Expression: GPL-3.0-only
Requires-Python: >=3.13
License-File: LICENSE
Requires-Dist: torch
Requires-Dist: valanga>=0.1.13
Requires-Dist: PyYAML
Requires-Dist: dacite
Requires-Dist: rich
Requires-Dist: chess
Provides-Extra: test
Requires-Dist: pytest>=8.4.1; extra == "test"
Requires-Dist: coverage; extra == "test"
Requires-Dist: pytest-cov>=6.0.0; extra == "test"
Provides-Extra: lint
Requires-Dist: ruff>=0.14.1; extra == "lint"
Requires-Dist: pylint>=3.3.8; extra == "lint"
Provides-Extra: typecheck
Requires-Dist: mypy>=1.18.2; extra == "typecheck"
Requires-Dist: pyright[nodejs]>=1.1.408; extra == "typecheck"
Requires-Dist: types-PyYAML>=6.0.12.12; extra == "typecheck"
Provides-Extra: dev
Requires-Dist: tox>=4.30.2; extra == "dev"
Requires-Dist: types-PyYAML>=6.0.12.12; extra == "dev"
Requires-Dist: ruff>=0.14.1; extra == "dev"
Requires-Dist: pylint>=3.3.8; extra == "dev"
Requires-Dist: black>=25.1.0; extra == "dev"
Requires-Dist: mypy>=1.18.2; extra == "dev"
Requires-Dist: pyright>=1.1.406; extra == "dev"
Requires-Dist: build; extra == "dev"
Requires-Dist: twine; extra == "dev"
Requires-Dist: sphinx; extra == "dev"
Requires-Dist: sphinx-rtd-theme; extra == "dev"
Requires-Dist: sphinx-autodoc-typehints; extra == "dev"
Requires-Dist: pre-commit; extra == "dev"
Dynamic: license-file
